pico_ioc_flask/__init__.py
pico_ioc_flask/_version.py
pico_ioc_flask/decorators.py
pico_ioc_flask/plugin.py
pico_ioc_flask-0.1.0.dist-info/licenses/LICENSE
pico_ioc_flask-0.1.0.dist-info/METADATA
pico_ioc_flask-0.1.0.dist-info/WHEEL
pico_ioc_flask-0.1.0.dist-info/top_level.txt
pico_ioc_flask-0.1.0.dist-info/RECORD
