Metadata-Version: 2.4
Name: pico-ioc-flask
Version: 0.1.0
Summary: Flask integration plugin for pico-ioc (routes/controllers via DI).
Author-email: David Perez Cabrera <dperezcabrera@gmail.com>
License: MIT License
Project-URL: Homepage, https://github.com/dperezcabrera/pico-ioc-flask
Project-URL: Repository, https://github.com/dperezcabrera/pico-ioc-flask
Project-URL: Issue Tracker, https://github.com/dperezcabrera/pico-ioc-flask/issues
Keywords: ioc,di,flask,dependency injection,controller,routes
Classifier: Development Status :: 3 - Alpha
Classifier: Programming Language :: Python :: 3
Classifier: Programming Language :: Python :: 3 :: Only
Classifier: Programming Language :: Python :: 3.8
Classifier: Programming Language :: Python :: 3.9
Classifier: Programming Language :: Python :: 3.10
Classifier: Programming Language :: Python :: 3.11
Classifier: Programming Language :: Python :: 3.12
Classifier: Programming Language :: Python :: 3.13
Classifier: License :: OSI Approved :: MIT License
Classifier: Framework :: Flask
Classifier: Operating System :: OS Independent
Requires-Python: >=3.8
License-File: LICENSE
Requires-Dist: Flask<4,>=2
Requires-Dist: pico-ioc>=0.4.0
Provides-Extra: dev
Requires-Dist: pytest>=8; extra == "dev"
Requires-Dist: tox>=4; extra == "dev"
Requires-Dist: tox-gh-actions>=3; extra == "dev"
Requires-Dist: ruff>=0.4; extra == "dev"
Requires-Dist: mypy>=1.8; extra == "dev"
Dynamic: license-file
